MANIFEST.in
README
README.md
setup.py
data/mount.fuse.dynamo
dynamo_fuse.egg-info/PKG-INFO
dynamo_fuse.egg-info/SOURCES.txt
dynamo_fuse.egg-info/dependency_links.txt
dynamo_fuse.egg-info/top_level.txt
dynamofuse/__init__.py
dynamofuse/base.py
dynamofuse/fs.py
dynamofuse/lock.py
dynamofuse/overwriteTest.py
dynamofuse/transTest.py
dynamofuse/records/__init__.py
dynamofuse/records/block.py
dynamofuse/records/directory.py
dynamofuse/records/file.py
dynamofuse/records/link.py
dynamofuse/records/node.py
dynamofuse/records/symlink.py