Metadata-Version: 1.1
Name: dynamo-fuse
Version: 0.1.4
Summary: Linux FUSE file system implementation with AWS DynamoDB as the storage
Home-page: https://github.com/denismo/dynamo-fuse
Author: Denis Mikhalkin
Author-email: denismo@yahoo.com
License: GNU General Public License, version 3
Platform: UNKNOWN
Classifier: Intended Audience :: Developers
Classifier: License :: OSI Approved :: GNU General Public License v3 (GPLv3)
Classifier: Operating System :: POSIX
Classifier: Operating System :: Unix
Classifier: Programming Language :: Python :: 2
Classifier: Programming Language :: Python :: 3
Classifier: Topic :: System :: Filesystems
Requires: fusepy(>2.0)
